<?xml version="1.0"?>
<Item xmlns="http://www.hybrasyl.com/XML/Hybrasyl/2020-02">
  <Name>Shirt</Name>
  <Comment>Armor - Male Peasant 01</Comment>
  <Properties>
    <Appearance Sprite="96" DisplaySprite="1" BodyStyle="Male"/>
    <Stackable Max="1"/>
    <Physical Value="100" Weight="2" Durability="2000"/>
    <Equipment Slot="Armor"/>
    <StatModifiers>
      <Combat Ac="-4"/>
    </StatModifiers>
    <Flags>Depositable Exchangeable Vendorable Tailorable</Flags>
    <Variants>
      <Group>Tailorable</Group>
    </Variants>
    <Vendor ShopTab="Armor-M"/>
    <Restrictions>
      <Level Min="1" Max="99"/>
      <Gender>Male</Gender>
    </Restrictions>
  </Properties>
</Item>
