<?xml version="1.0"?>
<Status xmlns="http://www.hybrasyl.com/XML/Hybrasyl/2020-02" Name="ReduceDamage" Icon="" Duration="" Tick="">
  <ProhibitedMessage>You can't do that right now</ProhibitedMessage>
  <Effects>
    <OnApply>
      <Animations>
        <Target Id="12" Speed="100"/>
      </Animations>
      <Sound Id="155"/>
      <Messages>
        <Target>Fuck I take less damage!</Target>
      </Messages>
      <Conditions>
        <Set>ReduceDamage</Set>
      </Conditions>
    </OnApply>
    <OnRemove>
      <Conditions>
        <Remove>ReduceDamage</Remove>
      </Conditions>
    </OnRemove>
    <OnExpire>
      <Conditions>
        <Remove>ReduceDamage</Remove>
      </Conditions>
    </OnExpire>
  </Effects>
</Status>
